LICENSE
README.md
README.rst
setup.cfg
setup.py
hide_code/LICENSE
hide_code/__init__.py
hide_code/auto-load-server-extension.txt
hide_code/auto-load.txt
hide_code/hide_code.js
hide_code/hide_code.py
hide_code/hide_code_config.json
hide_code/hide_code_config.py
hide_code/hide_code_html_exporter.py
hide_code/hide_code_latex_exporter.py
hide_code/hide_code_latexpdf_exporter.py
hide_code/hide_code_pdf_exporter.py
hide_code/hide_code_preprocessor.py
hide_code/hide_code_slides_exporter.py
hide_code/utils.py
hide_code.egg-info/PKG-INFO
hide_code.egg-info/SOURCES.txt
hide_code.egg-info/dependency_links.txt
hide_code.egg-info/entry_points.txt
hide_code.egg-info/requires.txt
hide_code.egg-info/top_level.txt
hide_code/Templates/hide_code_article.tplx
hide_code/Templates/hide_code_base_style.tplx
hide_code/Templates/hide_code_basic.tpl
hide_code/Templates/hide_code_full.tpl
hide_code/Templates/hide_code_slides.tpl
hide_code/test/test_hide_code.py
hide_code/test/utf-8 test.html
hide_code/test/utf-8 test.ipynb