Metadata-Version: 2.1
Name: hide-code
Version: 0.6.0
Summary: A Jupyter notebook extension to hide code, prompts and outputs.
Home-page: https://github.com/kirbs-/hide_code
Author: Chris Kirby
Author-email: kirbycm@gmail.com
License: MIT
Keywords: jupyter notebook presentation
Platform: UNKNOWN
Classifier: Development Status :: 5 - Production/Stable
Classifier: Intended Audience :: Developers
Classifier: Topic :: Scientific/Engineering
Classifier: License :: OSI Approved :: MIT License
Classifier: Programming Language :: Python :: 3.6
Classifier: Programming Language :: Python :: 3.7
Classifier: Programming Language :: Python :: 3.8
Provides-Extra: all
Provides-Extra: lab
